setup.py
fjp_helpers/__init__.py
fjp_helpers/animator.py
fjp_helpers/bc.py
fjp_helpers/misc.py
fjp_helpers/mpi.py
fjp_helpers.egg-info/PKG-INFO
fjp_helpers.egg-info/SOURCES.txt
fjp_helpers.egg-info/dependency_links.txt
fjp_helpers.egg-info/requires.txt
fjp_helpers.egg-info/top_level.txt