Metadata-Version: 1.1
Name: fjp-helpers
Version: 0.1.5
Summary: A collection of helper functions used to solve different equations.
Home-page: https://github.com/Poulin-Research-Group
Author: Dakota St. Laurent
Author-email: d.h.stlaurent@gmail.com
License: UNKNOWN
Download-URL: https://github.com/Poulin-Research-Group/helpers
Platform: UNKNOWN
